{
  "patient_id": "MDS-LR-DEL5Q-001",
  "comment": "Synthetic MDS-LR with isolated del(5q), transfusion-dependent anemia. Engine should select IND-MDS-LR-LENALIDOMIDE-DEL5Q (high TI rate ~67% per MDS-003).",

  "disease": {
    "id": "DIS-MDS-LR",
    "icd_o_3_morphology": "9989/3"
  },
  "line_of_therapy": 1,

  "biomarkers": {},

  "demographics": {
    "age": 70,
    "sex": "female",
    "ecog": 1,
    "fit_for_intensive_chemo": true,
    "fit_for_transplant": false,
    "pregnancy_status": "post_menopausal"
  },

  "findings": {
    "wbc_k_ul": 4.2,
    "hemoglobin_g_dl": 8.0,
    "platelets_k_ul": 145,
    "anc_k_ul": 2.0,
    "blast_percent_pb": 0,
    "blast_percent_bm": 2,
    "ipss_r_score": 2.5,
    "ipss_r_category": "low",
    "ipss_m_category": "low",
    "del_5q": true,
    "isolated_del_5q": true,
    "monosomy_7": false,
    "complex_karyotype": false,
    "tp53_mutation": false,
    "ring_sideroblasts_percent": 4,
    "transfusion_dependent": true,
    "transfusion_burden_units_per_8wk": 4,
    "epo_serum_mu_ml": 320,
    "active_uncontrolled_infection": false,
    "creatinine_clearance_ml_min": 64,
    "bilirubin_mg_dl": 0.6,
    "hbsag": "negative",
    "anti_hbc_total": "negative",
    "vte_history_or_high_risk": false
  },

  "clinical_record": {
    "diagnosis": {
      "primary_diagnosis": {
        "disease_entity": "MDS, isolated del(5q), transfusion-dependent anemia",
        "icd_o_3": "9989/3",
        "icd_10": "D46.C"
      },
      "ipss_r": {"score": 2.5, "category": "low"},
      "transfusion_dependence": {"category": "transfusion-dependent", "burden_per_8wk": 4}
    }
  }
}
