{
  "core": "openonco-engine-core.zip",
  "core_version": "5b3f9884e4d6",
  "diseases": {
    "DIS-AITL": "disease/openonco-dis-aitl.zip",
    "DIS-ALCL": "disease/openonco-dis-alcl.zip",
    "DIS-AML": "disease/openonco-dis-aml.zip",
    "DIS-ANAL-SCC": "disease/openonco-dis-anal-scc.zip",
    "DIS-APL": "disease/openonco-dis-apl.zip",
    "DIS-ATLL": "disease/openonco-dis-atll.zip",
    "DIS-B-ALL": "disease/openonco-dis-b-all.zip",
    "DIS-BCC": "disease/openonco-dis-bcc.zip",
    "DIS-BREAST": "disease/openonco-dis-breast.zip",
    "DIS-BURKITT": "disease/openonco-dis-burkitt.zip",
    "DIS-CERVICAL": "disease/openonco-dis-cervical.zip",
    "DIS-CHL": "disease/openonco-dis-chl.zip",
    "DIS-CHOLANGIOCARCINOMA": "disease/openonco-dis-cholangiocarcinoma.zip",
    "DIS-CHONDROSARCOMA": "disease/openonco-dis-chondrosarcoma.zip",
    "DIS-CLL": "disease/openonco-dis-cll.zip",
    "DIS-CML": "disease/openonco-dis-cml.zip",
    "DIS-CRC": "disease/openonco-dis-crc.zip",
    "DIS-DLBCL-NOS": "disease/openonco-dis-dlbcl-nos.zip",
    "DIS-EATL": "disease/openonco-dis-eatl.zip",
    "DIS-ENDOMETRIAL": "disease/openonco-dis-endometrial.zip",
    "DIS-EPITHELIOID-SARCOMA": "disease/openonco-dis-epithelioid-sarcoma.zip",
    "DIS-ESOPHAGEAL": "disease/openonco-dis-esophageal.zip",
    "DIS-ET": "disease/openonco-dis-et.zip",
    "DIS-FL": "disease/openonco-dis-fl.zip",
    "DIS-GASTRIC": "disease/openonco-dis-gastric.zip",
    "DIS-GBM": "disease/openonco-dis-gbm.zip",
    "DIS-GI-NET": "disease/openonco-dis-gi-net.zip",
    "DIS-GIST": "disease/openonco-dis-gist.zip",
    "DIS-GLIOMA-LOW-GRADE": "disease/openonco-dis-glioma-low-grade.zip",
    "DIS-GRANULOSA-CELL": "disease/openonco-dis-granulosa-cell.zip",
    "DIS-HCC": "disease/openonco-dis-hcc.zip",
    "DIS-HCL": "disease/openonco-dis-hcl.zip",
    "DIS-HCV-MZL": "disease/openonco-dis-hcv-mzl.zip",
    "DIS-HGBL-DH": "disease/openonco-dis-hgbl-dh.zip",
    "DIS-HNSCC": "disease/openonco-dis-hnscc.zip",
    "DIS-HSTCL": "disease/openonco-dis-hstcl.zip",
    "DIS-IFS": "disease/openonco-dis-ifs.zip",
    "DIS-IMT": "disease/openonco-dis-imt.zip",
    "DIS-JMML": "disease/openonco-dis-jmml.zip",
    "DIS-LAM": "disease/openonco-dis-lam.zip",
    "DIS-MASTOCYTOSIS": "disease/openonco-dis-mastocytosis.zip",
    "DIS-MCL": "disease/openonco-dis-mcl.zip",
    "DIS-MDS-HR": "disease/openonco-dis-mds-hr.zip",
    "DIS-MDS-LR": "disease/openonco-dis-mds-lr.zip",
    "DIS-MELANOMA": "disease/openonco-dis-melanoma.zip",
    "DIS-MENINGIOMA": "disease/openonco-dis-meningioma.zip",
    "DIS-MESOTHELIOMA": "disease/openonco-dis-mesothelioma.zip",
    "DIS-MF-SEZARY": "disease/openonco-dis-mf-sezary.zip",
    "DIS-MM": "disease/openonco-dis-mm.zip",
    "DIS-MPNST": "disease/openonco-dis-mpnst.zip",
    "DIS-MTC": "disease/openonco-dis-mtc.zip",
    "DIS-NK-T-NASAL": "disease/openonco-dis-nk-t-nasal.zip",
    "DIS-NLPBL": "disease/openonco-dis-nlpbl.zip",
    "DIS-NODAL-MZL": "disease/openonco-dis-nodal-mzl.zip",
    "DIS-NSCLC": "disease/openonco-dis-nsclc.zip",
    "DIS-OVARIAN": "disease/openonco-dis-ovarian.zip",
    "DIS-PCNSL": "disease/openonco-dis-pcnsl.zip",
    "DIS-PDAC": "disease/openonco-dis-pdac.zip",
    "DIS-PMBCL": "disease/openonco-dis-pmbcl.zip",
    "DIS-PMF": "disease/openonco-dis-pmf.zip",
    "DIS-PNET": "disease/openonco-dis-pnet.zip",
    "DIS-PROSTATE": "disease/openonco-dis-prostate.zip",
    "DIS-PTCL-NOS": "disease/openonco-dis-ptcl-nos.zip",
    "DIS-PTLD": "disease/openonco-dis-ptld.zip",
    "DIS-PV": "disease/openonco-dis-pv.zip",
    "DIS-RCC": "disease/openonco-dis-rcc.zip",
    "DIS-SALIVARY": "disease/openonco-dis-salivary.zip",
    "DIS-SCLC": "disease/openonco-dis-sclc.zip",
    "DIS-SOFT-TISSUE-SARCOMA": "disease/openonco-dis-soft-tissue-sarcoma.zip",
    "DIS-SPLENIC-MZL": "disease/openonco-dis-splenic-mzl.zip",
    "DIS-T-ALL": "disease/openonco-dis-t-all.zip",
    "DIS-T-PLL": "disease/openonco-dis-t-pll.zip",
    "DIS-TESTICULAR-GCT": "disease/openonco-dis-testicular-gct.zip",
    "DIS-TGCT": "disease/openonco-dis-tgct.zip",
    "DIS-THYROID-ANAPLASTIC": "disease/openonco-dis-thyroid-anaplastic.zip",
    "DIS-THYROID-PAPILLARY": "disease/openonco-dis-thyroid-papillary.zip",
    "DIS-UROTHELIAL": "disease/openonco-dis-urothelial.zip",
    "DIS-WM": "disease/openonco-dis-wm.zip"
  },
  "disease_versions": {
    "DIS-AITL": "29c4ffeec2b2",
    "DIS-ALCL": "4ede7184bbe9",
    "DIS-AML": "b3028499f60f",
    "DIS-ANAL-SCC": "2ad1e105284c",
    "DIS-APL": "04fccc21559d",
    "DIS-ATLL": "4f11b62b7f82",
    "DIS-B-ALL": "3f582d619926",
    "DIS-BCC": "55d0f0e050f2",
    "DIS-BREAST": "ae8f71c7eaa5",
    "DIS-BURKITT": "79c716be25eb",
    "DIS-CERVICAL": "84a6ef4f21c4",
    "DIS-CHL": "7526c37387d4",
    "DIS-CHOLANGIOCARCINOMA": "06fc4cec4f97",
    "DIS-CHONDROSARCOMA": "81139ab5e83c",
    "DIS-CLL": "1533569e76a9",
    "DIS-CML": "c54e219e59e1",
    "DIS-CRC": "e7bc95d6a96c",
    "DIS-DLBCL-NOS": "7e131735ff76",
    "DIS-EATL": "0ddf87c7dcd8",
    "DIS-ENDOMETRIAL": "3626fc3ae12f",
    "DIS-EPITHELIOID-SARCOMA": "c70c583dd5ec",
    "DIS-ESOPHAGEAL": "e4e8593a91ce",
    "DIS-ET": "1942e34ad07e",
    "DIS-FL": "e45649161ef4",
    "DIS-GASTRIC": "6d011ceb7713",
    "DIS-GBM": "1bfd8440b4fe",
    "DIS-GI-NET": "9e18807538eb",
    "DIS-GIST": "67e84df82268",
    "DIS-GLIOMA-LOW-GRADE": "333e77a74b6e",
    "DIS-GRANULOSA-CELL": "82044a155073",
    "DIS-HCC": "ada35779dc45",
    "DIS-HCL": "cad45030769c",
    "DIS-HCV-MZL": "8a7018db316f",
    "DIS-HGBL-DH": "bb0726e70ae5",
    "DIS-HNSCC": "748b90306cf3",
    "DIS-HSTCL": "ebcb077c6a6a",
    "DIS-IFS": "7541ff1408f0",
    "DIS-IMT": "42606a3392c0",
    "DIS-JMML": "f199b4269340",
    "DIS-LAM": "2c9c58a26d72",
    "DIS-MASTOCYTOSIS": "02e489df8445",
    "DIS-MCL": "b1f88e4c2a60",
    "DIS-MDS-HR": "61dc560c469d",
    "DIS-MDS-LR": "02d8fdb1d570",
    "DIS-MELANOMA": "9ea13c833b1b",
    "DIS-MENINGIOMA": "3b5cae79f02d",
    "DIS-MESOTHELIOMA": "a38ae3f75560",
    "DIS-MF-SEZARY": "37ecca9eae05",
    "DIS-MM": "25d9b72c29b3",
    "DIS-MPNST": "39d3f69af562",
    "DIS-MTC": "f8953d1a3949",
    "DIS-NK-T-NASAL": "45cfb5fd5d02",
    "DIS-NLPBL": "4637176e86aa",
    "DIS-NODAL-MZL": "5dabcfa011c3",
    "DIS-NSCLC": "7b45ce797773",
    "DIS-OVARIAN": "a9fdc337c894",
    "DIS-PCNSL": "05549e87a065",
    "DIS-PDAC": "dd300396b6bd",
    "DIS-PMBCL": "e8e186cc8ec1",
    "DIS-PMF": "a6c049214ff2",
    "DIS-PNET": "35e8abb0d5c8",
    "DIS-PROSTATE": "4a5abc8723b2",
    "DIS-PTCL-NOS": "6ba549953918",
    "DIS-PTLD": "bd72f439b776",
    "DIS-PV": "26f2f598b437",
    "DIS-RCC": "eee8deb3101a",
    "DIS-SALIVARY": "2f240cae02fd",
    "DIS-SCLC": "d721dcf0ef71",
    "DIS-SOFT-TISSUE-SARCOMA": "92fafdbfddb8",
    "DIS-SPLENIC-MZL": "ae2f857e9f01",
    "DIS-T-ALL": "b566010a072e",
    "DIS-T-PLL": "b06ed411b7fa",
    "DIS-TESTICULAR-GCT": "db8c413077a9",
    "DIS-TGCT": "140ae77fb2a2",
    "DIS-THYROID-ANAPLASTIC": "82878e6f37d8",
    "DIS-THYROID-PAPILLARY": "d0c60be2608a",
    "DIS-UROTHELIAL": "b40d9e57d4ec",
    "DIS-WM": "7f90ffc32710"
  },
  "icd_to_disease_id": {
    "9705/3": "DIS-AITL",
    "9714/3": "DIS-ALCL",
    "9861/3": "DIS-AML",
    "8070/3": "DIS-HNSCC",
    "9866/3": "DIS-APL",
    "9827/3": "DIS-ATLL",
    "9811/3": "DIS-B-ALL",
    "8090/3": "DIS-BCC",
    "8500/3": "DIS-SALIVARY",
    "9687/3": "DIS-BURKITT",
    "8160/3": "DIS-CHOLANGIOCARCINOMA",
    "9220/3": "DIS-CHONDROSARCOMA",
    "9823/3": "DIS-CLL",
    "9863/3": "DIS-CML",
    "8140/3": "DIS-PROSTATE",
    "9680/3": "DIS-PCNSL",
    "9717/3": "DIS-EATL",
    "8380/3": "DIS-ENDOMETRIAL",
    "8804/3": "DIS-EPITHELIOID-SARCOMA",
    "9962/3": "DIS-ET",
    "9690/3": "DIS-FL",
    "9440/3": "DIS-GBM",
    "8240/3": "DIS-PNET",
    "8936/3": "DIS-GIST",
    "9400/3": "DIS-GLIOMA-LOW-GRADE",
    "8620/3": "DIS-GRANULOSA-CELL",
    "9940/3": "DIS-HCL",
    "8170/3": "DIS-HCC",
    "9699/3": "DIS-NODAL-MZL",
    "9650/3": "DIS-CHL",
    "9716/3": "DIS-HSTCL",
    "8814/3": "DIS-IFS",
    "8825/1": "DIS-IMT",
    "9946/3": "DIS-JMML",
    "8894/1": "DIS-LAM",
    "9673/3": "DIS-MCL",
    "9740/3": "DIS-MASTOCYTOSIS",
    "9983/3": "DIS-MDS-HR",
    "9989/3": "DIS-MDS-LR",
    "8720/3": "DIS-MELANOMA",
    "9530/0": "DIS-MENINGIOMA",
    "9050/3": "DIS-MESOTHELIOMA",
    "9540/3": "DIS-MPNST",
    "8345/3": "DIS-MTC",
    "9732/3": "DIS-MM",
    "9700/3": "DIS-MF-SEZARY",
    "9719/3": "DIS-NK-T-NASAL",
    "9659/3": "DIS-NLPBL",
    "8046/3": "DIS-NSCLC",
    "8441/3": "DIS-OVARIAN",
    "9679/3": "DIS-PMBCL",
    "9961/3": "DIS-PMF",
    "9702/3": "DIS-PTCL-NOS",
    "9971/3": "DIS-PTLD",
    "9950/3": "DIS-PV",
    "8312/3": "DIS-RCC",
    "8041/3": "DIS-SCLC",
    "8800/3": "DIS-SOFT-TISSUE-SARCOMA",
    "9689/3": "DIS-SPLENIC-MZL",
    "9837/3": "DIS-T-ALL",
    "9834/3": "DIS-T-PLL",
    "9061/3": "DIS-TESTICULAR-GCT",
    "9252/1": "DIS-TGCT",
    "8021/3": "DIS-THYROID-ANAPLASTIC",
    "8260/3": "DIS-THYROID-PAPILLARY",
    "8120/3": "DIS-UROTHELIAL",
    "9671/3": "DIS-WM"
  }
}