{
  "core": "openonco-engine-core.zip",
  "core_version": "ccd3c2067c6b",
  "diseases": {
    "DIS-AITL": "disease/openonco-dis-aitl.zip",
    "DIS-ALCL": "disease/openonco-dis-alcl.zip",
    "DIS-AML": "disease/openonco-dis-aml.zip",
    "DIS-APL": "disease/openonco-dis-apl.zip",
    "DIS-ATLL": "disease/openonco-dis-atll.zip",
    "DIS-B-ALL": "disease/openonco-dis-b-all.zip",
    "DIS-BREAST": "disease/openonco-dis-breast.zip",
    "DIS-BURKITT": "disease/openonco-dis-burkitt.zip",
    "DIS-CERVICAL": "disease/openonco-dis-cervical.zip",
    "DIS-CHL": "disease/openonco-dis-chl.zip",
    "DIS-CHOLANGIOCARCINOMA": "disease/openonco-dis-cholangiocarcinoma.zip",
    "DIS-CHONDROSARCOMA": "disease/openonco-dis-chondrosarcoma.zip",
    "DIS-CLL": "disease/openonco-dis-cll.zip",
    "DIS-CML": "disease/openonco-dis-cml.zip",
    "DIS-CRC": "disease/openonco-dis-crc.zip",
    "DIS-DLBCL-NOS": "disease/openonco-dis-dlbcl-nos.zip",
    "DIS-EATL": "disease/openonco-dis-eatl.zip",
    "DIS-ENDOMETRIAL": "disease/openonco-dis-endometrial.zip",
    "DIS-ESOPHAGEAL": "disease/openonco-dis-esophageal.zip",
    "DIS-ET": "disease/openonco-dis-et.zip",
    "DIS-FL": "disease/openonco-dis-fl.zip",
    "DIS-GASTRIC": "disease/openonco-dis-gastric.zip",
    "DIS-GBM": "disease/openonco-dis-gbm.zip",
    "DIS-GIST": "disease/openonco-dis-gist.zip",
    "DIS-GLIOMA-LOW-GRADE": "disease/openonco-dis-glioma-low-grade.zip",
    "DIS-HCC": "disease/openonco-dis-hcc.zip",
    "DIS-HCL": "disease/openonco-dis-hcl.zip",
    "DIS-HCV-MZL": "disease/openonco-dis-hcv-mzl.zip",
    "DIS-HGBL-DH": "disease/openonco-dis-hgbl-dh.zip",
    "DIS-HNSCC": "disease/openonco-dis-hnscc.zip",
    "DIS-HSTCL": "disease/openonco-dis-hstcl.zip",
    "DIS-IFS": "disease/openonco-dis-ifs.zip",
    "DIS-IMT": "disease/openonco-dis-imt.zip",
    "DIS-MASTOCYTOSIS": "disease/openonco-dis-mastocytosis.zip",
    "DIS-MCL": "disease/openonco-dis-mcl.zip",
    "DIS-MDS-HR": "disease/openonco-dis-mds-hr.zip",
    "DIS-MDS-LR": "disease/openonco-dis-mds-lr.zip",
    "DIS-MELANOMA": "disease/openonco-dis-melanoma.zip",
    "DIS-MF-SEZARY": "disease/openonco-dis-mf-sezary.zip",
    "DIS-MM": "disease/openonco-dis-mm.zip",
    "DIS-MPNST": "disease/openonco-dis-mpnst.zip",
    "DIS-MTC": "disease/openonco-dis-mtc.zip",
    "DIS-NK-T-NASAL": "disease/openonco-dis-nk-t-nasal.zip",
    "DIS-NLPBL": "disease/openonco-dis-nlpbl.zip",
    "DIS-NODAL-MZL": "disease/openonco-dis-nodal-mzl.zip",
    "DIS-NSCLC": "disease/openonco-dis-nsclc.zip",
    "DIS-OVARIAN": "disease/openonco-dis-ovarian.zip",
    "DIS-PCNSL": "disease/openonco-dis-pcnsl.zip",
    "DIS-PDAC": "disease/openonco-dis-pdac.zip",
    "DIS-PMBCL": "disease/openonco-dis-pmbcl.zip",
    "DIS-PMF": "disease/openonco-dis-pmf.zip",
    "DIS-PROSTATE": "disease/openonco-dis-prostate.zip",
    "DIS-PTCL-NOS": "disease/openonco-dis-ptcl-nos.zip",
    "DIS-PTLD": "disease/openonco-dis-ptld.zip",
    "DIS-PV": "disease/openonco-dis-pv.zip",
    "DIS-RCC": "disease/openonco-dis-rcc.zip",
    "DIS-SALIVARY": "disease/openonco-dis-salivary.zip",
    "DIS-SCLC": "disease/openonco-dis-sclc.zip",
    "DIS-SPLENIC-MZL": "disease/openonco-dis-splenic-mzl.zip",
    "DIS-T-ALL": "disease/openonco-dis-t-all.zip",
    "DIS-T-PLL": "disease/openonco-dis-t-pll.zip",
    "DIS-THYROID-ANAPLASTIC": "disease/openonco-dis-thyroid-anaplastic.zip",
    "DIS-THYROID-PAPILLARY": "disease/openonco-dis-thyroid-papillary.zip",
    "DIS-UROTHELIAL": "disease/openonco-dis-urothelial.zip",
    "DIS-WM": "disease/openonco-dis-wm.zip"
  },
  "disease_versions": {
    "DIS-AITL": "104e75787339",
    "DIS-ALCL": "212d10de1fcf",
    "DIS-AML": "8ce4c2871e3b",
    "DIS-APL": "f9987fa94073",
    "DIS-ATLL": "f005311f125e",
    "DIS-B-ALL": "3cb9231862ec",
    "DIS-BREAST": "47f36108ad8b",
    "DIS-BURKITT": "f2ddf99e8bca",
    "DIS-CERVICAL": "efb5828e4f8f",
    "DIS-CHL": "d8ea2cd7adae",
    "DIS-CHOLANGIOCARCINOMA": "564cdfceca11",
    "DIS-CHONDROSARCOMA": "978a9807d0af",
    "DIS-CLL": "6f355b727e2b",
    "DIS-CML": "7e5de3603700",
    "DIS-CRC": "a2585f01c4aa",
    "DIS-DLBCL-NOS": "3b2eb4209a4f",
    "DIS-EATL": "4ae054f3dc52",
    "DIS-ENDOMETRIAL": "ed1b85f744fa",
    "DIS-ESOPHAGEAL": "1cf1fde24447",
    "DIS-ET": "2b7035270d8c",
    "DIS-FL": "fde98cae2d34",
    "DIS-GASTRIC": "6161576a98bc",
    "DIS-GBM": "3421bf5aaad5",
    "DIS-GIST": "42679cf9a027",
    "DIS-GLIOMA-LOW-GRADE": "1f985b550426",
    "DIS-HCC": "7a152aa14036",
    "DIS-HCL": "e345b8324270",
    "DIS-HCV-MZL": "b7dfdd46665a",
    "DIS-HGBL-DH": "b9d17e80f690",
    "DIS-HNSCC": "25b60e855607",
    "DIS-HSTCL": "077d34763e10",
    "DIS-IFS": "9f083261b60e",
    "DIS-IMT": "279b3dabe869",
    "DIS-MASTOCYTOSIS": "37fe08099a4e",
    "DIS-MCL": "e43bb7e2dc44",
    "DIS-MDS-HR": "4b2f9477cc40",
    "DIS-MDS-LR": "8252de86912f",
    "DIS-MELANOMA": "c8398cfa211a",
    "DIS-MF-SEZARY": "f3473d8e5ea3",
    "DIS-MM": "41066db51045",
    "DIS-MPNST": "80f97950f63e",
    "DIS-MTC": "cc4e31a43c8f",
    "DIS-NK-T-NASAL": "2ee70e91d95d",
    "DIS-NLPBL": "9d60464f92d8",
    "DIS-NODAL-MZL": "c27927534c33",
    "DIS-NSCLC": "d6fa99338036",
    "DIS-OVARIAN": "965121c09e21",
    "DIS-PCNSL": "fa5c1f2095e4",
    "DIS-PDAC": "4d2522c96370",
    "DIS-PMBCL": "b1979f9141e1",
    "DIS-PMF": "96ed26ba663a",
    "DIS-PROSTATE": "fe19e7a13891",
    "DIS-PTCL-NOS": "b7240b2e3790",
    "DIS-PTLD": "07bad4a5bab0",
    "DIS-PV": "8fc7f5422b92",
    "DIS-RCC": "6e87c88041ec",
    "DIS-SALIVARY": "a334b5c68219",
    "DIS-SCLC": "1f7b9931a27a",
    "DIS-SPLENIC-MZL": "5d0c12d03432",
    "DIS-T-ALL": "4449d0d1df47",
    "DIS-T-PLL": "d6b5d8fcd29d",
    "DIS-THYROID-ANAPLASTIC": "9bde769fa139",
    "DIS-THYROID-PAPILLARY": "be92db60c219",
    "DIS-UROTHELIAL": "ff6a6b08e46d",
    "DIS-WM": "869413b9769b"
  },
  "icd_to_disease_id": {
    "9705/3": "DIS-AITL",
    "9714/3": "DIS-ALCL",
    "9861/3": "DIS-AML",
    "9866/3": "DIS-APL",
    "9827/3": "DIS-ATLL",
    "9811/3": "DIS-B-ALL",
    "8500/3": "DIS-SALIVARY",
    "9687/3": "DIS-BURKITT",
    "8070/3": "DIS-HNSCC",
    "8160/3": "DIS-CHOLANGIOCARCINOMA",
    "9220/3": "DIS-CHONDROSARCOMA",
    "9823/3": "DIS-CLL",
    "9863/3": "DIS-CML",
    "8140/3": "DIS-PROSTATE",
    "9680/3": "DIS-PCNSL",
    "9717/3": "DIS-EATL",
    "8380/3": "DIS-ENDOMETRIAL",
    "9962/3": "DIS-ET",
    "9690/3": "DIS-FL",
    "9440/3": "DIS-GBM",
    "8936/3": "DIS-GIST",
    "9400/3": "DIS-GLIOMA-LOW-GRADE",
    "9940/3": "DIS-HCL",
    "8170/3": "DIS-HCC",
    "9699/3": "DIS-NODAL-MZL",
    "9650/3": "DIS-CHL",
    "9716/3": "DIS-HSTCL",
    "8814/3": "DIS-IFS",
    "8825/1": "DIS-IMT",
    "9673/3": "DIS-MCL",
    "9740/3": "DIS-MASTOCYTOSIS",
    "9983/3": "DIS-MDS-HR",
    "9989/3": "DIS-MDS-LR",
    "8720/3": "DIS-MELANOMA",
    "9540/3": "DIS-MPNST",
    "8345/3": "DIS-MTC",
    "9732/3": "DIS-MM",
    "9700/3": "DIS-MF-SEZARY",
    "9719/3": "DIS-NK-T-NASAL",
    "9659/3": "DIS-NLPBL",
    "8046/3": "DIS-NSCLC",
    "8441/3": "DIS-OVARIAN",
    "9679/3": "DIS-PMBCL",
    "9961/3": "DIS-PMF",
    "9702/3": "DIS-PTCL-NOS",
    "9971/3": "DIS-PTLD",
    "9950/3": "DIS-PV",
    "8312/3": "DIS-RCC",
    "8041/3": "DIS-SCLC",
    "9689/3": "DIS-SPLENIC-MZL",
    "9837/3": "DIS-T-ALL",
    "9834/3": "DIS-T-PLL",
    "8021/3": "DIS-THYROID-ANAPLASTIC",
    "8260/3": "DIS-THYROID-PAPILLARY",
    "8120/3": "DIS-UROTHELIAL",
    "9671/3": "DIS-WM"
  }
}